racetrackgym/__init__.py
racetrackgym/argument_parser.py
racetrackgym/environment.py
racetrackgym/evaluator.py
racetrackgym/graphic.py
racetrackgym/logger.py
racetrackgym/maps/barto-big.track
racetrackgym/maps/barto-big_scales/barto-big_scaled_10.track
racetrackgym/maps/barto-big_scales/barto-big_scaled_2.track
racetrackgym/maps/barto-big_scales/barto-big_scaled_3.track
racetrackgym/maps/barto-big_scales/barto-big_scaled_4.track
racetrackgym/maps/barto-big_scales/barto-big_scaled_5.track
racetrackgym/maps/barto-big_scales/barto-big_scaled_6.track
racetrackgym/maps/barto-big_scales/barto-big_scaled_7.track
racetrackgym/maps/barto-big_scales/barto-big_scaled_8.track
racetrackgym/maps/barto-big_scales/barto-big_scaled_9.track
racetrackgym/maps/barto-small.track
racetrackgym/maps/barto-small_scales/barto-small_scaled_2.track
racetrackgym/maps/barto-small_scales/barto-small_scaled_4.track
racetrackgym/maps/corner/1-2-3.track
racetrackgym/maps/corner/1-4-3.track
racetrackgym/maps/corner/2-1-4.track
racetrackgym/maps/corner/2-3-4.track
racetrackgym/maps/corner/3-2-1.track
racetrackgym/maps/corner/3-4-1.track
racetrackgym/maps/corner/4-1-2.track
racetrackgym/maps/corner/4-3-2.track
racetrackgym/maps/diverse/barrier.txt
racetrackgym/maps/diverse/bottleneck.txt
racetrackgym/maps/diverse/corner.txt
racetrackgym/maps/diverse/diagonal.txt
racetrackgym/maps/diverse/pyramid.txt
racetrackgym/maps/diverse/ring.txt
racetrackgym/maps/diverse/spiral.txt
racetrackgym/maps/diverse/straighton.txt
racetrackgym/maps/diverse/uturn.txt
racetrackgym/maps/diverse/wavy.txt
racetrackgym/maps/double-track.track
racetrackgym/maps/empty-40x40.track
racetrackgym/maps/empty-80x80.track
racetrackgym/maps/hansen-bigger.track
racetrackgym/maps/large-curves.track
racetrackgym/maps/maze-and-shortcuts.track
racetrackgym/maps/maze-extended.track
racetrackgym/maps/maze-small.track
racetrackgym/maps/maze.track
racetrackgym/maps/nook/nook_1.potentials
racetrackgym/maps/nook/nook_1.track
racetrackgym-0.3.0.dist-info/LICENSE
racetrackgym-0.3.0.dist-info/METADATA
racetrackgym-0.3.0.dist-info/WHEEL
racetrackgym-0.3.0.dist-info/RECORD
