Metadata-Version: 2.3
Name: racetrackgym
Version: 0.3.0
Summary: Gymnasium-compatible python simulation of the 'Racetrack' game.
License: MIT
Author: Timo P. Gros
Author-email: timopgros@cs.uni-saarland.de
Maintainer: Joshua Meyer
Maintainer-email: joshua.meyer@cs.uni-saarland.de
Requires-Python: >= 3.9
Classifier: License :: OSI Approved :: MIT License
Classifier: Programming Language :: Python :: 3
Classifier: Programming Language :: Python :: 3.9
Classifier: Programming Language :: Python :: 3.10
Classifier: Programming Language :: Python :: 3.11
Classifier: Programming Language :: Python :: 3.12
Classifier: Programming Language :: Python :: 3.13
Requires-Dist: Pillow (>=8.4.0)
Requires-Dist: argparse (>=1.4.0)
Requires-Dist: matplotlib (>=3.4.3)
Requires-Dist: numpy (>=1.21.4)
